osidb_bindings/__init__.py
osidb_bindings/constants.py
osidb_bindings/exceptions.py
osidb_bindings/helpers.py
osidb_bindings/iterators.py
osidb_bindings/session.py
osidb_bindings/utils.py
osidb_bindings/bindings/__init__.py
osidb_bindings/bindings/python_client/__init__.py
osidb_bindings/bindings/python_client/client.py
osidb_bindings/bindings/python_client/errors.py
osidb_bindings/bindings/python_client/py.typed
osidb_bindings/bindings/python_client/types.py
osidb_bindings/bindings/python_client/api/__init__.py
osidb_bindings/bindings/python_client/api/auth/__init__.py
osidb_bindings/bindings/python_client/api/auth/auth_token_create.py
osidb_bindings/bindings/python_client/api/auth/auth_token_refresh_create.py
osidb_bindings/bindings/python_client/api/auth/auth_token_refresh_retrieve.py
osidb_bindings/bindings/python_client/api/auth/auth_token_retrieve.py
osidb_bindings/bindings/python_client/api/auth/auth_token_verify_create.py
osidb_bindings/bindings/python_client/api/collectors/__init__.py
osidb_bindings/bindings/python_client/api/collectors/collectors_api_v1_status_retrieve.py
osidb_bindings/bindings/python_client/api/collectors/collectors_healthy_retrieve.py
osidb_bindings/bindings/python_client/api/collectors/collectors_retrieve.py
osidb_bindings/bindings/python_client/api/exploits/__init__.py
osidb_bindings/bindings/python_client/api/exploits/exploits_api_v1_collect_update.py
osidb_bindings/bindings/python_client/api/exploits/exploits_api_v1_cve_map_retrieve.py
osidb_bindings/bindings/python_client/api/exploits/exploits_api_v1_epss_list.py
osidb_bindings/bindings/python_client/api/exploits/exploits_api_v1_flaw_data_list.py
osidb_bindings/bindings/python_client/api/exploits/exploits_api_v1_report_data_list.py
osidb_bindings/bindings/python_client/api/exploits/exploits_api_v1_report_date_retrieve.py
osidb_bindings/bindings/python_client/api/exploits/exploits_api_v1_report_explanations_retrieve.py
osidb_bindings-5.4.0.dist-info/licenses/LICENSE
osidb_bindings-5.4.0.dist-info/METADATA
osidb_bindings-5.4.0.dist-info/WHEEL
osidb_bindings-5.4.0.dist-info/top_level.txt
osidb_bindings-5.4.0.dist-info/RECORD
