Metadata-Version: 2.4
Name: osidb_bindings
Version: 5.4.0
Summary: Python bindings for accessing OSIDB API
Home-page: https://github.com/RedHatProductSecurity/osidb-bindings
Author: Jakub Frejlach, Red Hat Product Security
Author-email: jfrejlac@redhat.com
Project-URL: Changelog, https://github.com/RedHatProductSecurity/osidb-bindings/blob/master/CHANGELOG.md
Project-URL: Documentation, https://github.com/RedHatProductSecurity/osidb-bindings/blob/master/TUTORIAL.md
Project-URL: Source, https://github.com/RedHatProductSecurity/osidb-bindings
Classifier: Programming Language :: Python :: 3
Requires-Python: >=3.6
License-File: LICENSE
Requires-Dist: aiohttp
Requires-Dist: attrs
Requires-Dist: requests
Requires-Dist: requests-gssapi
Requires-Dist: python-dateutil
Dynamic: author
Dynamic: author-email
Dynamic: classifier
Dynamic: description
Dynamic: description-content-type
Dynamic: home-page
Dynamic: license-file
Dynamic: project-url
Dynamic: requires-dist
Dynamic: requires-python
Dynamic: summary
